{
  "Acon": "Aconitum Napellus",
  "Ars": "Arsenicum Album",
  "Bell": "Belladonna",
  "Bry": "Bryonia Alba",
  "Calc": "Calcarea Carbonica",
  "Puls": "Pulsatilla Nigricans",
  "Lyc": "Lycopodium Clavatum",
  "Sulph": "Sulphur",
  "Sep": "Sepia Officinalis",
  "Nit-ac": "Nitricum Acidum",
  "Merc": "Mercurius Solubilis",
  "Nux-v": "Nux Vomica",
  "Phos": "Phosphorus",
  "Sil": "Silicea Terra",
  "Thuj": "Thuja Occidentalis",
  "Rhus-t": "Rhus Toxicodendron",
  "Apis": "Apis Mellifica",
  "Arn": "Arnica Montana",
  "Gels": "Gelsemium Sempervirens",
  "Ign": "Ignatia Amara",
  "Staph": "Staphisagria",
  "Lach": "Lachesis Mutus",
  "Nat-m": "Natrum Muriaticum",
  "Nat-c": "Natrum Carbonicum",
  "Nat-s": "Natrum Sulphuricum",
  "Kali-c": "Kali Carbonicum",
  "Kali-bi": "Kali Bichromicum",
  "Arg-n": "Argentum Nitricum",
  "Aur": "Aurum Metallicum",
  "Hyos": "Hyoscyamus Niger",
  "Stram": "Stramonium",
  "Op": "Opium",
  "Verat": "Veratrum Album",
  "China": "Cinchona Officinalis",
  "Cupr": "Cuprum Metallicum",
  "Zinc": "Zincum Metallicum",
  "Plb": "Plumbum Metallicum",
  "Hep": "Hepar Sulphuris Calcareum",
  "Graph": "Graphites",
  "Ant-t": "Antimonium Tartaricum",
  "Ant-c": "Antimonium Crudum",
  "Ipec": "Ipecacuanha",
  "Cham": "Chamomilla",
  "Coff": "Coffea Cruda",
  "Cina": "Cina Maritima",
  "Dros": "Drosera Rotundifolia",
  "Rumx": "Rumex Crispus",
  "Spong": "Spongia Tosta",
  "Canth": "Cantharis Vesicatoria",
  "Sars": "Sarsaparilla Officinalis",
  "Berb": "Berberis Vulgaris",
  "Chel": "Chelidonium Majus",
  "Aloe": "Aloe Socotrina",
  "Card-m": "Carduus Marianus",
  "Crat": "Crataegus Oxyacantha",
  "Dig": "Digitalis Purpurea",
  "Cact": "Cactus Grandiflorus",
  "Glon": "Glonoinum",
  "Spig": "Spigelia Anthelmia",
  "Con": "Conium Maculatum",
  "Hydr": "Hydrastis Canadensis",
  "Ph-ac": "Phosphoricum Acidum",
  "Pic-ac": "Picricum Acidum",
  "Mur-ac": "Muriaticum Acidum",
  "Fl-ac": "Fluoricum Acidum",
  "Led": "Ledum Palustre",
  "Ruta": "Ruta Graveolens",
  "Symph": "Symphytum Officinale",
  "Hyper": "Hypericum Perforatum",
  "Calen": "Calendula Officinalis",
  "Ham": "Hamamelis Virginiana",
  "Mill": "Millefolium",
  "Sec": "Secale Cornutum",
  "Ustil": "Ustilago Maydis",
  "Vib": "Viburnum Opulus",
  "Helon": "Helonias Dioica",
  "Sabina": "Sabina",
  "Trill": "Trillium Pendulum",
  "Erig": "Erigeron Canadense",
  "Pyrog": "Pyrogenium",
  "Anthrac": "Anthracinum",
  "Psor": "Psorinum",
  "Med": "Medorrhinum",
  "Syph": "Syphilinum",
  "Tub": "Tuberculinum Koch",
  "Bac": "Bacillinum",
  "Tarent": "Tarentula Hispana",
  "Tarentula": "Tarentula Hispana",
  "Plat": "Platina",
  "Platina": "Platina",
  "Alum": "Alumina",
  "Alumina": "Alumina"
}
